compbiolab/__init__.py
compbiolab-0.1.6.2.dist-info/DESCRIPTION.rst
compbiolab-0.1.6.2.dist-info/METADATA
compbiolab-0.1.6.2.dist-info/RECORD
compbiolab-0.1.6.2.dist-info/WHEEL
compbiolab-0.1.6.2.dist-info/metadata.json
compbiolab-0.1.6.2.dist-info/top_level.txt
