Metadata-Version: 2.0
Name: compbiolab
Version: 0.1.6.2
Summary: Common functions for the CompBioLab researchers
Home-page: https://github.com/miqueleg/compbiolab
Author: Miquel Estevez
Author-email: miquel.estevez@udg.edu
License: MIT
Platform: UNKNOWN
Requires-Dist: matplotlib
Requires-Dist: numpy
Requires-Dist: pandas
Requires-Dist: pytraj
Requires-Dist: scipy
Requires-Dist: seaborn
